llm_behavior_eval/__init__.py
llm_behavior_eval/__main__.py
llm_behavior_eval/evaluate.py
llm_behavior_eval/evaluation_utils/base_evaluator.py
llm_behavior_eval/evaluation_utils/custom_dataset.py
llm_behavior_eval/evaluation_utils/dataset_config.py
llm_behavior_eval/evaluation_utils/enums.py
llm_behavior_eval/evaluation_utils/eval_config.py
llm_behavior_eval/evaluation_utils/evaluate_factory.py
llm_behavior_eval/evaluation_utils/free_text_bias_evaluator.py
llm_behavior_eval/evaluation_utils/free_text_hallu_evaluator.py
llm_behavior_eval/evaluation_utils/free_text_injection_evaluator.py
llm_behavior_eval/evaluation_utils/prompts.py
llm_behavior_eval/evaluation_utils/util_functions.py
llm_behavior_eval-0.1.3.dist-info/licenses/LICENSE
llm_behavior_eval-0.1.3.dist-info/METADATA
llm_behavior_eval-0.1.3.dist-info/WHEEL
llm_behavior_eval-0.1.3.dist-info/entry_points.txt
llm_behavior_eval-0.1.3.dist-info/top_level.txt
llm_behavior_eval-0.1.3.dist-info/RECORD
