Metadata-Version: 2.4
Name: llm-behavior-eval
Version: 0.1.3
Summary: Evaluate large-language models for undesirable behaviors such as bias.
Author-email: Hirundo <dev@hirundo.io>
License: MIT License
Project-URL: Homepage, https://github.com/Hirundo-io/llm-behavior-eval
Keywords: dataset,machine learning,data science,data engineering,large language models,LLMs evaluation,bias evaluation,bias in LLMs
Classifier: License :: OSI Approved :: MIT License
Classifier: Programming Language :: Python
Classifier: Programming Language :: Python :: 3
Requires-Python: >=3.10
License-File: LICENSE
Requires-Dist: datasets<4.0.0
Requires-Dist: numpy<3.0.0
Requires-Dist: pandas<3.0.0
Requires-Dist: pydantic<3.0.0
Requires-Dist: pydantic_settings<3.0.0
Requires-Dist: torch<3.0.0
Requires-Dist: transformers<5.0.0
Requires-Dist: networkx<4.0.0
Requires-Dist: pytest<9.0.0
Requires-Dist: typer<1.0.0
Requires-Dist: accelerate<2.0.0
Requires-Dist: bitsandbytes<1.0.0
Provides-Extra: dev
Requires-Dist: ruff<1.0.0,>=0.11.11; extra == "dev"
Requires-Dist: bumpver>=2024.1130; extra == "dev"
Requires-Dist: pyright>=1.1.399; extra == "dev"
Requires-Dist: pytest>=8.3.5; extra == "dev"
Provides-Extra: docs
Requires-Dist: sphinx>=8.0.0; extra == "docs"
Dynamic: license-file
